Workbook

Sheet Supuestos
A1: MODELO FINANCIERO INTEGRADO — METANOIA SMX
A2: Cifras en $ millones ARS · pesos constantes · TC y supuestos en azul son editables
A4: PARÁMETROS GENERALES
A5: Tipo de cambio (ARS/USD) | B5: 1450
A6: Reinversión tecnológica (% de utilidad) | B6: 0.15
A7: Nota: modelo en pesos constantes. La indexación 100% IPC del MSP mantiene su valor real ≈ constante.
A9: LÍNEA A — CONVENIO MSP (Ministerio)
A10: Ingreso mensual ($ millones) | B10: 80
A11: Meses por año | B11: 12
A12: Costo de prestación (% del ingreso) — COMPLETAR con AUREN | B12: 0.5
A13: Horizonte estratégico (años, supuesto político ≥4) | B13: 4
A15: LÍNEA C — CURSOS (base: programa anual laparoscopía)
A16: Ingreso USD — Año 1 (ocup. 50%) | B16: 186000
A17: Ingreso USD — Año 2 (ocup. 70%) | B17: 340000
A18: Ingreso USD — Año 3 (ocup. 85%) | B18: 507000
A19: Ingreso USD — Año 4 | B19: 507000
A20: Margen bruto Año 1 | B20: 0.35
A21: Margen bruto Año 2 | B21: 0.5
A22: Margen bruto Año 3-4 | B22: 0.6
A23: Factor de escala de cursos desde Año 2 — objetivo ~4 (4 cursos/mes 2027) | B23: 1
A25: LÍNEA D — COFRADIA (suscripciones)
A26: Ingreso USD — Año 1 | B26: 28535
A27: Ingreso USD — Año 2 | B27: 73876
A28: Crecimiento anual Año 3-4 (sobre año previo) | B28: 0.4
A29: Costo expertos USD — Año 1 | B29: 18270
A30: Costo expertos USD — Año 2 | B30: 39150
A31: Costo expertos (% del ingreso) Año 3-4 | B31: 0.53
A33: COSTO FIJO COMPARTIDO (redes + médicos curadores)
A34: Costo mensual ($ millones) | B34: 10
A35: Meses por año | B35: 12
A37: ASIGNACIÓN INTERNA DEL COSTO COMPARTIDO AL MSP (% por año)
A38: Año 1 (el convenio subsidia la comunidad) | B38: 0.8
A39: Año 2 | B39: 0.6
A40: Año 3 | B40: 0.4
A41: Año 4 | B41: 0.3
A43: Nota: la asignación es atribución interna; no cambia la utilidad total, refleja la política de que el MSP subsidie la construcción de comunidad al inicio.

Sheet Modelo 4 años
A1: MODELO CONSOLIDADO — 4 AÑOS
A2: $ millones ARS · pesos constantes
A3: Concepto | B3: Año 1 | C3: Año 2 | D3: Año 3 | E3: Año 4
A4: INGRESOS
A5: Línea A — Convenio MSP | B5: =Supuestos!$B$10*Supuestos!$B$11 -> 960 | C5: =Supuestos!$B$10*Supuestos!$B$11 -> 960 | D5: =Supuestos!$B$10*Supuestos!$B$11 -> 960 | E5: =Supuestos!$B$10*Supuestos!$B$11 -> 960
A6: Línea C — Cursos (laparoscopía + escala) | B6: =Supuestos!B16*Supuestos!$B$5/1000000 -> 269.7 | C6: =Supuestos!B17*Supuestos!$B$5/1000000*Supuestos!$B$23 -> 493 | D6: =Supuestos!B18*Supuestos!$B$5/1000000*Supuestos!$B$23 -> 735.15 | E6: =Supuestos!B19*Supuestos!$B$5/1000000*Supuestos!$B$23 -> 735.15
A7: Línea D — COFRADIA (suscripciones) | B7: =Supuestos!B26*Supuestos!$B$5/1000000 -> 41.37575 | C7: =Supuestos!B27*Supuestos!$B$5/1000000 -> 107.1202 | D7: =C7*(1+Supuestos!$B$28) -> 149.96828 | E7: =D7*(1+Supuestos!$B$28) -> 209.95559
A8: TOTAL INGRESOS | B8: =SUM(B5:B7) -> 1271.0757 | C8: =SUM(C5:C7) -> 1560.1202 | D8: =SUM(D5:D7) -> 1845.1183 | E8: =SUM(E5:E7) -> 1905.1056
A10: COSTOS
A11: Costo prestación MSP | B11: =B5*Supuestos!$B$12 -> 480 | C11: =C5*Supuestos!$B$12 -> 480 | D11: =D5*Supuestos!$B$12 -> 480 | E11: =E5*Supuestos!$B$12 -> 480
A12: Costo directo Cursos | B12: =B6*(1-Supuestos!$B$20) -> 175.305 | C12: =C6*(1-Supuestos!$B$21) -> 246.5 | D12: =D6*(1-Supuestos!$B$22) -> 294.06 | E12: =E6*(1-Supuestos!$B$22) -> 294.06
A13: Costo expertos COFRADIA | B13: =Supuestos!B29*Supuestos!$B$5/1000000 -> 26.4915 | C13: =Supuestos!B30*Supuestos!$B$5/1000000 -> 56.7675 | D13: =D7*Supuestos!$B$31 -> 79.483188 | E13: =E7*Supuestos!$B$31 -> 111.27646
A14: Costo fijo compartido | B14: =Supuestos!$B$34*Supuestos!$B$35 -> 120 | C14: =Supuestos!$B$34*Supuestos!$B$35 -> 120 | D14: =Supuestos!$B$34*Supuestos!$B$35 -> 120 | E14: =Supuestos!$B$34*Supuestos!$B$35 -> 120
A15: TOTAL COSTOS | B15: =SUM(B11:B14) -> 801.7965 | C15: =SUM(C11:C14) -> 903.2675 | D15: =SUM(D11:D14) -> 973.54319 | E15: =SUM(E11:E14) -> 1005.3365
A17: RESULTADO
A18: Utilidad operativa | B18: =B8-B15 -> 469.27925 | C18: =C8-C15 -> 656.8527 | D18: =D8-D15 -> 871.57509 | E18: =E8-E15 -> 899.76913
A19: Margen operativo % | B19: =B18/B8 -> 0.36919849 | C19: =C18/C8 -> 0.42102698 | D19: =D18/D8 -> 0.47236814 | E19: =E18/E8 -> 0.47229357
A20: Reinversión tecnológica (15%) | B20: =MAX(B18,0)*Supuestos!$B$6 -> 70.391887 | C20: =MAX(C18,0)*Supuestos!$B$6 -> 98.527905 | D20: =MAX(D18,0)*Supuestos!$B$6 -> 130.73626 | E20: =MAX(E18,0)*Supuestos!$B$6 -> 134.96537
A21: Utilidad después de reinversión | B21: =B18-B20 -> 398.88736 | C21: =C18-C20 -> 558.32479 | D21: =D18-D20 -> 740.83883 | E21: =E18-E20 -> 764.80376
A23: AUTONOMÍA / DEPENDENCIA
A24: % ingresos Convenio MSP (dependencia) | B24: =B5/B8 -> 0.75526577 | C24: =C5/C8 -> 0.6153372 | D24: =D5/D8 -> 0.52029185 | E24: =E5/E8 -> 0.50390908
A25: % ingresos privados (C+D) | B25: =(B6+B7)/B8 -> 0.24473423 | C25: =(C6+C7)/C8 -> 0.3846628 | D25: =(D6+D7)/D8 -> 0.47970815 | E25: =(E6+E7)/E8 -> 0.49609092
A26: Meta dependencia MSP < 40% | B26: =IF(B24<0.4,"✓ cumple","✗ no") -> ✗ no | C26: =IF(C24<0.4,"✓ cumple","✗ no") -> ✗ no | D26: =IF(D24<0.4,"✓ cumple","✗ no") -> ✗ no | E26: =IF(E24<0.4,"✓ cumple","✗ no") -> ✗ no
A28: ATRIBUCIÓN INTERNA DEL COSTO COMPARTIDO
A29: Cargado al Convenio MSP | B29: =B14*Supuestos!$B$38 -> 96 | C29: =C14*Supuestos!$B$39 -> 72 | D29: =D14*Supuestos!$B$40 -> 48 | E29: =E14*Supuestos!$B$41 -> 36
A30: Cargado a Cursos + COFRADIA | B30: =B14-B29 -> 24 | C30: =C14-C29 -> 48 | D30: =D14-D29 -> 72 | E30: =E14-E29 -> 84

Sheet Notas
A1: NOTAS, SUPUESTOS Y PENDIENTES
A3: MONEDA Y HORIZONTE
A4: • Modelo en pesos constantes (reales) a TC $1.450. La indexación 100% IPC del MSP mantiene su valor real ≈ constante; por eso el convenio se mantiene plano en términos reales.
A5: • Para una vista nominal en pesos haría falta una proyección de inflación (validar con AUREN).
A7: DATOS A COMPLETAR / VALIDAR CON AUREN (celdas amarillas)
A8: • Costo de prestación del Convenio MSP (hoy 50% placeholder): instructores de residentes, insumos, amortización. Es el dato que más mueve la utilidad. SIN ESTO, la utilidad es estimada.
A9: • Costo fijo compartido $10M/mes (redes + curadores): confirmar si es el total y si crece al sumar especialidades.
A11: SUPUESTOS CLAVE
A12: • Línea C (cursos): ingresos y márgenes del Resumen Ejecutivo de laparoscopía (USD), convertidos a $1.450.
A13: • Factor de escala de cursos (celda B23 de Supuestos): por defecto 1.0 (solo laparoscopía). Tu objetivo declarado es ~4 cursos/mes desde 2027 (Año 2): poné 4 para ver ese escenario.
A14: • Línea D (COFRADIA): Años 1-2 del modelo de suscripciones (escenario esperado); Años 3-4 extrapolados con crecimiento (celda B28).
A15: • Política de costos: el costo compartido se carga mayormente al MSP en los primeros años (Supuestos B38-B41), para que el convenio subsidie la construcción de la comunidad.
... A22: ESTE MODELO NO ES ASESORAMIENTO FINANCIERO. Es una herramienta de gestión para decidir con datos; validar supuestos y resultados con AUREN antes de tomar decisiones.
